mcp_server_pubtator3/__init__.py
mcp_server_pubtator3/__main__.py
mcp_server_pubtator3/pubtator_client.py
mcp_server_pubtator3/server.py
mcp_server_pubtator3-0.1.9.dist-info/METADATA
mcp_server_pubtator3-0.1.9.dist-info/WHEEL
mcp_server_pubtator3-0.1.9.dist-info/entry_points.txt
mcp_server_pubtator3-0.1.9.dist-info/top_level.txt
mcp_server_pubtator3-0.1.9.dist-info/RECORD
