Metadata-Version: 2.4
Name: mcp-server-pubtator3
Version: 0.1.9
Summary: PubTator3 API compatible with the MCP agent protocol
Home-page: https://github.com/QIngyuanfl/mcp-server-pubtator3.git
Author: Qingyuan Zhang
Author-email: Qingyuan Zhang <598153063@qq.com>
Maintainer-email: Qingyuan Zhang <598153063@qq.com>
License-Expression: MIT
Project-URL: Repository, https://github.com/QIngyuanfl/mcp-server-pubtator3.git
Project-URL: Issues, https://github.com/QIngyuanfl/mcp-server-pubtator3/issues
Requires-Python: >=3.10
Requires-Dist: aiohttp
Requires-Dist: aiolimiter
Requires-Dist: mcp[cli]
